poetry_demo/__init__.py
poetry_demo_gregory_ionic-0.1.1.dist-info/METADATA
poetry_demo_gregory_ionic-0.1.1.dist-info/WHEEL
poetry_demo_gregory_ionic-0.1.1.dist-info/RECORD
