Metadata-Version: 2.1
Name: poetry-demo-gregory-ionic
Version: 0.1.1
Summary: 
Author: Gregory Kohler
Author-email: gregory@ionicapi.com
Requires-Python: >=3.12,<4.0
Classifier: Programming Language :: Python :: 3
Classifier: Programming Language :: Python :: 3.12
Requires-Dist: pendulum (>=3.0.0,<4.0.0)
